data_lib/__init__.py
data_lib/data_utils.py
data_lib/io_data_handling.py
data_lib-1.0.2.dist-info/METADATA
data_lib-1.0.2.dist-info/RECORD
data_lib-1.0.2.dist-info/WHEEL
data_lib-1.0.2.dist-info/top_level.txt
tests/__init__.py
tests/tests_data_utils_module.py
