Metadata-Version: 2.1
Name: data_lib
Version: 1.0.2
Summary: Data handling and manipulation library
Home-page: https://pypi.org/project/data-lib
Author: Adam Jarzebak
Author-email: adam@jarzebak.eu
License: UNKNOWN
Platform: UNKNOWN
Classifier: Programming Language :: Python :: 3
Classifier: License :: OSI Approved :: MIT License
Classifier: Operating System :: OS Independent
